leak_snek/__init__.py
leak_snek/decorators/__init__.py
leak_snek/decorators/aio/__init__.py
leak_snek/decorators/aio/rate_limit.py
leak_snek/decorators/rate_limit.py
leak_snek/interfaces/__init__.py
leak_snek/interfaces/limiters/__init__.py
leak_snek/interfaces/limiters/aio/__init__.py
leak_snek/interfaces/limiters/aio/rate_limiter.py
leak_snek/interfaces/limiters/rate_limiter.py
leak_snek/interfaces/mutexes/__init__.py
leak_snek/interfaces/mutexes/aio/__init__.py
leak_snek/interfaces/mutexes/aio/mutex.py
leak_snek/interfaces/mutexes/mutex.py
leak_snek/interfaces/storages/__init__.py
leak_snek/interfaces/storages/aio/__init__.py
leak_snek/interfaces/storages/aio/rate_store.py
leak_snek/interfaces/storages/rate_store.py
leak_snek/interfaces/values/__init__.py
leak_snek/interfaces/values/rate.py
leak_snek/interfaces/values/rate_limit.py
leak_snek/limiters/__init__.py
leak_snek/limiters/aio/__init__.py
leak_snek/limiters/aio/leaky_bucket.py
leak_snek/limiters/leaky_bucket.py
leak_snek/mutexes/__init__.py
leak_snek/mutexes/memory_mutex.py
leak_snek/py.typed
leak_snek/shortcuts/__init__.py
leak_snek/shortcuts/rate_limit.py
leak_snek/storages/__init__.py
leak_snek/storages/memory_storage.py
leak_snek-0.3.2.dist-info/LICENSE
leak_snek-0.3.2.dist-info/METADATA
leak_snek-0.3.2.dist-info/WHEEL
leak_snek-0.3.2.dist-info/RECORD
