Metadata-Version: 2.1
Name: leak-snek
Version: 0.3.2
Summary: Leak Snek is a Python library that provides a flexible and extensible implementation of rate limiting for your applications
Home-page: https://github.com/WinterCitizen/leak_snek
License: MIT
Keywords: rate,limit,typed,rate_limit,leaky_buket
Author: Daniil Fedyaev
Author-email: wintercitizen@outlook.com
Requires-Python: >=3.12,<4.0
Classifier: License :: OSI Approved :: MIT License
Classifier: Operating System :: OS Independent
Classifier: Programming Language :: Python :: 3
Project-URL: Repository, https://github.com/WinterCitizen/leak_snek
